asjohnston_pypi_test/__init__.py
asjohnston_pypi_test-0.0.4.dist-info/METADATA
asjohnston_pypi_test-0.0.4.dist-info/WHEEL
asjohnston_pypi_test-0.0.4.dist-info/top_level.txt
asjohnston_pypi_test-0.0.4.dist-info/RECORD
