Metadata-Version: 2.4
Name: asjohnston_pypi_test
Version: 0.0.4
Summary: A dummy package to test publishing to PyPI
Author-email: Andrew Johnston <asjohnston@alaska.edu>
License-Expression: BSD-3-Clause
Project-URL: Homepage, https://github.com/asjohnston-asf/pypi-test
Classifier: Programming Language :: Python :: 3
Requires-Python: >=3.10
Provides-Extra: develop
Requires-Dist: build; extra == "develop"
